edpm/__init__.py
edpm/__main__.py
edpm/version.py
edpm/cli/__init__.py
edpm/cli/add.py
edpm/cli/clean.py
edpm/cli/config.py
edpm/cli/env.py
edpm/cli/info.py
edpm/cli/init.py
edpm/cli/install.py
edpm/cli/pwd.py
edpm/cli/req.py
edpm/cli/rm.py
edpm/engine/__init__.py
edpm/engine/api.py
edpm/engine/commands.py
edpm/engine/composed_recipe.py
edpm/engine/config.py
edpm/engine/git_cmake_recipe.py
edpm/engine/lockfile.py
edpm/engine/output.py
edpm/engine/planfile.py
edpm/engine/recipe.py
edpm/engine/recipe_manager.py
edpm/engine/fetchers/__init__.py
edpm/engine/generators/__init__.py
edpm/engine/generators/cmake_generator.py
edpm/engine/generators/environment_generator.py
edpm/engine/generators/steps.py
edpm/engine/makers/__init__.py
edpm/recipes/__init__.py
edpm/recipes/acts.py
edpm/recipes/actssvg.py
edpm/recipes/algorithms.py
edpm/recipes/catch2.py
edpm/recipes/clhep.py
edpm/recipes/dd4hep.py
edpm/recipes/disruptor-cpp.py
edpm/recipes/edm4eic.py
edpm/recipes/edm4hep.py
edpm/recipes/eicrecon.py
edpm/recipes/eigen3.py
edpm/recipes/epic.py
edpm/recipes/evio.py
edpm/recipes/fastjet.py
edpm/recipes/fmt.py
edpm/recipes/geant4.py
edpm/recipes/hepmc3.py
edpm/recipes/irt.py
edpm/recipes/jana2.py
edpm/recipes/jana4ml4fpga.py
edpm/recipes/npdet.py
edpm/recipes/podio.py
edpm/recipes/root.py
edpm/recipes/vgm.py
edpm/templates/__init__.py
edpm/templates/default-plan.edpm.yaml
edpm/templates/eic-plan.edpm.yaml
edpm/templates/test-plan.edpm.yaml
edpm-3.1.19.dist-info/licenses/LICENSE
edpm-3.1.19.dist-info/METADATA
edpm-3.1.19.dist-info/WHEEL
edpm-3.1.19.dist-info/entry_points.txt
edpm-3.1.19.dist-info/top_level.txt
edpm-3.1.19.dist-info/RECORD
