Metadata-Version: 2.4
Name: edpm
Version: 3.1.19
Summary: Easy Dependency Package Manager
Author-email: Dmitry Romanov <romanov@jlab.org>
License-Expression: MIT
Project-URL: Homepage, https://github.com/DraTeots/edpm
Classifier: Development Status :: 4 - Beta
Classifier: Programming Language :: Python :: 3
Classifier: Programming Language :: Python :: 3.9
License-File: LICENSE
Requires-Dist: click
Requires-Dist: appdirs
Requires-Dist: ruamel.yaml
Provides-Extra: dev
Requires-Dist: pytest; extra == "dev"
Requires-Dist: build; extra == "dev"
Requires-Dist: twine; extra == "dev"
Requires-Dist: keyrings.alt; extra == "dev"
Dynamic: license-file
